synthol/__init__.py
synthol/context.py
synthol/injector.py
synthol/provider.py
synthol/scope.py
synthol/utils.py
synthol-0.1.1.dist-info/LICENSE
synthol-0.1.1.dist-info/METADATA
synthol-0.1.1.dist-info/WHEEL
synthol-0.1.1.dist-info/top_level.txt
synthol-0.1.1.dist-info/RECORD
