Metadata-Version: 2.1
Name: synthol
Version: 0.1.1
Summary: Simple Python3 dependency injector
Home-page: https://gitlab.com/redballoonsecurity/synthol
Author: Red Balloon Security
License: UNKNOWN
Project-URL: Bug Tracker, https://gitlab.com/redballoonsecurity/synthol/-/issues
Platform: UNKNOWN
Classifier: Intended Audience :: Developers
Classifier: License :: OSI Approved :: MIT License
Classifier: Natural Language :: English
Classifier: Topic :: Software Development
Requires-Python: >=3.7
Requires-Dist: typing-inspect (~=0.7.1)
Provides-Extra: test
Requires-Dist: mypy (==0.942) ; extra == 'test'
Requires-Dist: pytest (~=7.1.1) ; extra == 'test'
Requires-Dist: pytest-asyncio (~=0.18.3) ; extra == 'test'
Requires-Dist: pytest-cov (~=3.0.0) ; extra == 'test'
